djangocms_picture/__init__.py
djangocms_picture/cms_plugins.py
djangocms_picture/forms.py
djangocms_picture/models.py
djangocms_picture/locale/af/LC_MESSAGES/django.mo
djangocms_picture/locale/af/LC_MESSAGES/django.po
djangocms_picture/locale/ar/LC_MESSAGES/django.mo
djangocms_picture/locale/ar/LC_MESSAGES/django.po
djangocms_picture/locale/be/LC_MESSAGES/django.mo
djangocms_picture/locale/be/LC_MESSAGES/django.po
djangocms_picture/locale/bg/LC_MESSAGES/django.mo
djangocms_picture/locale/bg/LC_MESSAGES/django.po
djangocms_picture/locale/bn/LC_MESSAGES/django.mo
djangocms_picture/locale/bn/LC_MESSAGES/django.po
djangocms_picture/locale/ca/LC_MESSAGES/django.mo
djangocms_picture/locale/ca/LC_MESSAGES/django.po
djangocms_picture/locale/cmn/LC_MESSAGES/django.mo
djangocms_picture/locale/cmn/LC_MESSAGES/django.po
djangocms_picture/locale/cs/LC_MESSAGES/django.mo
djangocms_picture/locale/cs/LC_MESSAGES/django.po
djangocms_picture/locale/cy/LC_MESSAGES/django.mo
djangocms_picture/locale/cy/LC_MESSAGES/django.po
djangocms_picture/locale/da/LC_MESSAGES/django.mo
djangocms_picture/locale/da/LC_MESSAGES/django.po
djangocms_picture/locale/de/LC_MESSAGES/django.mo
djangocms_picture/locale/de/LC_MESSAGES/django.po
djangocms_picture/locale/el/LC_MESSAGES/django.mo
djangocms_picture/locale/el/LC_MESSAGES/django.po
djangocms_picture/locale/en/LC_MESSAGES/django.mo
djangocms_picture/locale/en/LC_MESSAGES/django.po
djangocms_picture/locale/es/LC_MESSAGES/django.mo
djangocms_picture/locale/es/LC_MESSAGES/django.po
djangocms_picture/locale/es_AR/LC_MESSAGES/django.mo
djangocms_picture/locale/es_AR/LC_MESSAGES/django.po
djangocms_picture/locale/es_BO/LC_MESSAGES/django.mo
djangocms_picture/locale/es_BO/LC_MESSAGES/django.po
djangocms_picture/locale/es_DO/LC_MESSAGES/django.mo
djangocms_picture/locale/es_DO/LC_MESSAGES/django.po
djangocms_picture/locale/et/LC_MESSAGES/django.mo
djangocms_picture/locale/et/LC_MESSAGES/django.po
djangocms_picture/locale/eu/LC_MESSAGES/django.mo
djangocms_picture-4.1.1.dist-info/LICENSE
djangocms_picture-4.1.1.dist-info/METADATA
djangocms_picture-4.1.1.dist-info/WHEEL
djangocms_picture-4.1.1.dist-info/top_level.txt
djangocms_picture-4.1.1.dist-info/RECORD
